MANIFEST.in
README.md
requirements.txt
setup.cfg
setup.py
lambda_tools/__init__.py
lambda_tools/build.py
lambda_tools/command.py
lambda_tools/configuration.py
lambda_tools/deploy.py
lambda_tools/factoryfactory.py
lambda_tools/mapper.py
lambda_tools.egg-info/PKG-INFO
lambda_tools.egg-info/SOURCES.txt
lambda_tools.egg-info/dependency_links.txt
lambda_tools.egg-info/entry_points.txt
lambda_tools.egg-info/not-zip-safe
lambda_tools.egg-info/requires.txt
lambda_tools.egg-info/top_level.txt