Metadata-Version: 1.1
Name: lambda-tools
Version: 0.1.5
Summary: A toolkit for creating and deploying Python code to AWS Lambda
Home-page: https://github.com/jammycakes/lambda-tools
Author: James McKay
Author-email: code@jamesmckay.net
License: MIT
Download-URL: https://github.com/jammycakes/lambda-tools/archive/0.1.5.tar.gz
Keywords: aws-lambda,aws
Platform: UNKNOWN
Classifier: Development Status :: 3 - Alpha
Classifier: License :: OSI Approved :: MIT License
Classifier: Programming Language :: Python :: 3.6
